CHANGES.rst
CONTRIBUTORS.rst
MANIFEST.in
README.rst
setup.py
docs/LICENSE.GPL
docs/LICENSE.rst
src/collective/__init__.py
src/collective.tinymceplugins.embedly.egg-info/PKG-INFO
src/collective.tinymceplugins.embedly.egg-info/SOURCES.txt
src/collective.tinymceplugins.embedly.egg-info/dependency_links.txt
src/collective.tinymceplugins.embedly.egg-info/entry_points.txt
src/collective.tinymceplugins.embedly.egg-info/namespace_packages.txt
src/collective.tinymceplugins.embedly.egg-info/not-zip-safe
src/collective.tinymceplugins.embedly.egg-info/requires.txt
src/collective.tinymceplugins.embedly.egg-info/top_level.txt
src/collective/tinymceplugins/__init__.py
src/collective/tinymceplugins/embedly/__init__.py
src/collective/tinymceplugins/embedly/config.py
src/collective/tinymceplugins/embedly/configure.zcml
src/collective/tinymceplugins/embedly/patches.py
src/collective/tinymceplugins/embedly/setuphandlers.py
src/collective/tinymceplugins/embedly/skins.zcml
src/collective/tinymceplugins/embedly/Extensions/Install.py
src/collective/tinymceplugins/embedly/browser/__init__.py
src/collective/tinymceplugins/embedly/browser/configure.zcml
src/collective/tinymceplugins/embedly/browser/views.py
src/collective/tinymceplugins/embedly/profiles/default/collective-tinymceplugins-embedly-default.txt
src/collective/tinymceplugins/embedly/profiles/default/import_steps.xml
src/collective/tinymceplugins/embedly/profiles/default/jsregistry.xml
src/collective/tinymceplugins/embedly/profiles/default/metadata.xml
src/collective/tinymceplugins/embedly/profiles/default/skins.xml
src/collective/tinymceplugins/embedly/profiles/default/tinymce.xml
src/collective/tinymceplugins/embedly/profiles/uninstall/collective-tinymceplugins-embedly-uninstall.txt
src/collective/tinymceplugins/embedly/profiles/uninstall/jsregistry.xml
src/collective/tinymceplugins/embedly/profiles/uninstall/metadata.xml
src/collective/tinymceplugins/embedly/profiles/uninstall/skins.xml
src/collective/tinymceplugins/embedly/profiles/uninstall/tinymce.xml
src/collective/tinymceplugins/embedly/skins/tinymce_embedly/tinymce_embedly/editor_plugin.js
src/collective/tinymceplugins/embedly/skins/tinymce_embedly/tinymce_embedly/editor_plugin_src.js
src/collective/tinymceplugins/embedly/skins/tinymce_embedly/tinymce_embedly/embed.htm.pt
src/collective/tinymceplugins/embedly/skins/tinymce_embedly/tinymce_embedly/tiny_mce_popup.js
src/collective/tinymceplugins/embedly/skins/tinymce_embedly/tinymce_embedly/tinymce_html.js
