Metadata-Version: 1.1
Name: collective.tinymceplugins.embedly
Version: 1.0.2
Summary: Integration of the Embedly TinyMCE plugin with Plone
Home-page: http://github.com/collective/collective.tinymceplugins.embedly
Author: Netsight Internet Solutions Limited
Author-email: info@netsight.co.uk
License: GPL v2
Platform: UNKNOWN
Classifier: Framework :: Plone
Classifier: Framework :: Plone :: 4.0
Classifier: Framework :: Plone :: 4.1
Classifier: Framework :: Plone :: 4.3
Classifier: License :: OSI Approved :: GNU General Public License v2 (GPLv2)
Classifier: Operating System :: OS Independent
Classifier: Programming Language :: JavaScript
Classifier: Programming Language :: Python
Classifier: Topic :: Text Processing :: Markup :: HTML
